latex_utils/__init__.py
latex_utils/main.py
table_img_latex_gen-1.0.0.dist-info/METADATA
table_img_latex_gen-1.0.0.dist-info/WHEEL
table_img_latex_gen-1.0.0.dist-info/top_level.txt
table_img_latex_gen-1.0.0.dist-info/RECORD
