Metadata-Version: 2.1
Name: table-img-latex-gen
Version: 1.0.0
Summary: Module for generation table and image in LaTeX
Author: Anny-waay
Author-email: ann.komova@gmail.com
License: MIT
Keywords: LaTex
Classifier: Programming Language :: Python :: 3.10
Classifier: License :: OSI Approved :: MIT License
Classifier: Operating System :: OS Independent
Requires-Python: >=3.7
Requires-Dist: requests>=2.25.1
